pdf_annot/__init__.py
pdf_annot/annotation.py
pdf_annot/attach.py
pdf_annot/extract.py
pdf_annot-0.1.0.dist-info/LICENSE
pdf_annot-0.1.0.dist-info/METADATA
pdf_annot-0.1.0.dist-info/WHEEL
pdf_annot-0.1.0.dist-info/top_level.txt
pdf_annot-0.1.0.dist-info/RECORD
