Metadata-Version: 2.1
Name: pdf-annot
Version: 0.1.0
Summary: Utilities to extract and merge PDF annotations
Home-page: https://github.com/xiahongze/pdf_annot
Author: Hongze Xia
Maintainer: Hongze Xia
Maintainer-email: hongzex@gmail.com
License: GPL-3
Platform: UNKNOWN
Requires-Dist: python-version (>=3.7)
Requires-Dist: PyMuPDF (>=1.16)
